fslfeatsetup/Comments.py
fslfeatsetup/EVs.py
fslfeatsetup/FSF.py
fslfeatsetup/FSFLabels.py
fslfeatsetup/__init__.py
fslfeatsetup-0.4.8.dist-info/LICENSE.md
fslfeatsetup-0.4.8.dist-info/METADATA
fslfeatsetup-0.4.8.dist-info/WHEEL
fslfeatsetup-0.4.8.dist-info/top_level.txt
fslfeatsetup-0.4.8.dist-info/RECORD
