Metadata-Version: 2.1
Name: fslfeatsetup
Version: 0.4.8
Summary: a small set of tools for create FSL FEAT .fsf configuration files
Home-page: https://github.com/chris-langfield/pyfsf
Author: Chris Langfield
Author-email: cal2254@cumc.columbia.edu
License: Attribution-NonCommercial-ShareAlike
Platform: UNKNOWN
Classifier: Development Status :: 3 - Alpha
Requires-Python: >=3.7
License-File: LICENSE.md
Requires-Dist: fslpy
